odoo/addons/mute_notification_user_autosubscribe/README.rst
odoo/addons/mute_notification_user_autosubscribe/__init__.py
odoo/addons/mute_notification_user_autosubscribe/__manifest__.py
odoo/addons/mute_notification_user_autosubscribe/data/mail_message_subtype_data.xml
odoo/addons/mute_notification_user_autosubscribe/i18n/it.po
odoo/addons/mute_notification_user_autosubscribe/i18n/mute_notification_user_autosubscribe.pot
odoo/addons/mute_notification_user_autosubscribe/models/__init__.py
odoo/addons/mute_notification_user_autosubscribe/models/mail_thread.py
odoo/addons/mute_notification_user_autosubscribe/models/res_users.py
odoo/addons/mute_notification_user_autosubscribe/models/user_autosubscribe_mute.py
odoo/addons/mute_notification_user_autosubscribe/readme/CONFIGURE.md
odoo/addons/mute_notification_user_autosubscribe/readme/CONTRIBUTORS.md
odoo/addons/mute_notification_user_autosubscribe/readme/DESCRIPTION.md
odoo/addons/mute_notification_user_autosubscribe/readme/ROADMAP.md
odoo/addons/mute_notification_user_autosubscribe/readme/USAGE.md
odoo/addons/mute_notification_user_autosubscribe/security/ir.model.access.csv
odoo/addons/mute_notification_user_autosubscribe/static/description/icon.png
odoo/addons/mute_notification_user_autosubscribe/static/description/index.html
odoo/addons/mute_notification_user_autosubscribe/tests/__init__.py
odoo/addons/mute_notification_user_autosubscribe/tests/test_mute_user_sutosubscribe.py
odoo/addons/mute_notification_user_autosubscribe/views/user_autosubscribe_mute_views.xml
odoo_addon_mute_notification_user_autosubscribe-17.0.1.0.0.4.dist-info/METADATA
odoo_addon_mute_notification_user_autosubscribe-17.0.1.0.0.4.dist-info/WHEEL
odoo_addon_mute_notification_user_autosubscribe-17.0.1.0.0.4.dist-info/top_level.txt
odoo_addon_mute_notification_user_autosubscribe-17.0.1.0.0.4.dist-info/RECORD
